{
  "title": "Network - Event Throughput",
  "visState": "{\"title\":\"Network - Event Throughput\",\"type\":\"metrics\",\"params\":{\"id\":\"429af7e0-3d5b-11e7-8b9d-ddc45b5f6d00\",\"type\":\"gauge\",\"series\":[{\"id\":\"429af7e1-3d5b-11e7-8b9d-ddc45b5f6d00\",\"color\":\"rgba(0,156,224,1)\",\"split_mode\":\"everything\",\"metrics\":[{\"id\":\"429af7e2-3d5b-11e7-8b9d-ddc45b5f6d00\",\"type\":\"count\"},{\"settings\":\"\",\"minimize\":0,\"window\":\"\",\"model\":\"linear\",\"id\":\"5faf9430-3d5b-11e7-8b9d-ddc45b5f6d00\",\"type\":\"moving_average\",\"field\":\"429af7e2-3d5b-11e7-8b9d-ddc45b5f6d00\"},{\"script\":\"params.mvgAvg != 0 ? params.mvgAvg / 60 : params.mvgAvg\",\"id\":\"2e992f10-4692-11e7-8116-65b4628ff93f\",\"type\":\"calculation\",\"variables\":[{\"id\":\"30c47380-4692-11e7-8116-65b4628ff93f\",\"name\":\"mvgAvg\",\"field\":\"5faf9430-3d5b-11e7-8b9d-ddc45b5f6d00\"}]}],\"seperate_axis\":0,\"axis_position\":\"right\",\"formatter\":\"number\",\"chart_type\":\"line\",\"line_width\":1,\"point_size\":1,\"fill\":0.5,\"stacked\":\"none\",\"label\":\"Event Throughput\",\"value_template\":\"{{value}}  / s\"}],\"time_field\":\"deviceReceiptTime\",\"index_pattern\":\"cef-*\",\"interval\":\"1m\",\"axis_position\":\"left\",\"axis_formatter\":\"number\",\"show_legend\":1,\"filter\":\"categoryDeviceType:\\\"Firewall\\\" OR categoryDeviceGroup:\\\"/IDS/Network\\\" OR categoryDeviceGroup:\\\"/VPN\\\" \",\"bar_color_rules\":[{\"id\":\"77dd4e80-3d5b-11e7-8b9d-ddc45b5f6d00\"}],\"background_color_rules\":[{\"id\":\"798c5e10-3d5b-11e7-8b9d-ddc45b5f6d00\"}],\"gauge_color_rules\":[{\"value\":0,\"id\":\"988f35d0-3d5b-11e7-8b9d-ddc45b5f6d00\",\"gauge\":null}],\"gauge_width\":10,\"gauge_inner_width\":10,\"gauge_style\":\"half\",\"gauge_max\":\"\"},\"aggs\":[],\"listeners\":{}}",
  "uiStateJSON": "{}",
  "description": "",
  "version": 1,
  "kibanaSavedObjectMeta": {
    "searchSourceJSON": "{\"query\":{\"query_string\":{\"query\":\"*\"}},\"filter\":[]}"
  }
}